bilalmodule/__init__.py
bilalmodule/core.py
bilalmodule-0.2.dist-info/licenses/LICENSE
bilalmodule-0.2.dist-info/METADATA
bilalmodule-0.2.dist-info/WHEEL
bilalmodule-0.2.dist-info/top_level.txt
bilalmodule-0.2.dist-info/RECORD
